mkdocs_new_features_notifier/__init__.py
mkdocs_new_features_notifier/plugin.py
mkdocs_new_features_notifier-0.1.6.dist-info/LICENSE
mkdocs_new_features_notifier-0.1.6.dist-info/METADATA
mkdocs_new_features_notifier-0.1.6.dist-info/WHEEL
mkdocs_new_features_notifier-0.1.6.dist-info/entry_points.txt
mkdocs_new_features_notifier-0.1.6.dist-info/top_level.txt
mkdocs_new_features_notifier-0.1.6.dist-info/RECORD
