Metadata-Version: 2.1
Name: mkdocs-new-features-notifier
Version: 0.1.6
Summary: A MkDocs plugin for new features detection
Home-page: https://github.com/obuya
Author: Kevin Obuya
Author-email: kevobuya@gmail.com
License: MIT
Keywords: mkdocs
Platform: UNKNOWN
Classifier: Development Status :: 4 - Beta
Classifier: Intended Audience :: Developers
Classifier: Intended Audience :: Information Technology
Classifier: License :: OSI Approved :: MIT License
Classifier: Programming Language :: Python
Classifier: Programming Language :: Python :: 3 :: Only
Classifier: Programming Language :: Python :: 3.4
Classifier: Programming Language :: Python :: 3.5
Classifier: Programming Language :: Python :: 3.6
Classifier: Programming Language :: Python :: 3.7
Requires-Python: >=3.4
Requires-Dist: mkdocs (>=1.0.4)
